streamfield/__init__.py
streamfield/apps.py
streamfield/blocks.py
streamfield/conf.py
streamfield/exceptions.py
streamfield/helpers.py
streamfield/logging.py
streamfield/processors.py
streamfield/typing.py
streamfield/urls.py
streamfield/utils.py
streamfield/admin/__init__.py
streamfield/admin/base.py
streamfield/admin/views.py
streamfield/field/__init__.py
streamfield/field/forms.py
streamfield/field/models.py
streamfield/field/widgets.py
streamfield/static/streamfield/dist/widget.css
streamfield/static/streamfield/dist/widget.js
streamfield/static/streamfield/dist/widget.js.map
streamfield/static/streamfield/dist/assets/sortable.svg
streamfield/static/streamfield/dist/assets/spinner.svg
streamfield/templates/streamfield/widget.html
streamfield/templates/streamfield/admin/block.html
streamfield/templates/streamfield/admin/buttons.html
streamfield/templates/streamfield/admin/invalid_block.html
streamfield/templatetags/__init__.py
streamfield/templatetags/streamfield.py
paper_streamfield-0.8.0.dist-info/LICENSE
paper_streamfield-0.8.0.dist-info/METADATA
paper_streamfield-0.8.0.dist-info/WHEEL
paper_streamfield-0.8.0.dist-info/top_level.txt
paper_streamfield-0.8.0.dist-info/RECORD
